python_jira_plus/__init__.py
python_jira_plus/describe_allowed_value.py
python_jira_plus/jira_plus.py
python_jira_plus-2.0.1.dist-info/licenses/LICENSE
python_jira_plus-2.0.1.dist-info/METADATA
python_jira_plus-2.0.1.dist-info/WHEEL
python_jira_plus-2.0.1.dist-info/top_level.txt
python_jira_plus-2.0.1.dist-info/RECORD
