Metadata-Version: 2.4
Name: python-jira-plus
Version: 2.0.1
Summary: Enhanced Python client for JIRA with better error handling, pagination, and metadata validation.
Home-page: https://github.com/aviz92/python-jira-plus
Author: Avi Zaguri
Author-email: 
Project-URL: Repository, https://github.com/aviz92/python-jira-plus
Requires-Python: >=3.11
License-File: LICENSE
Requires-Dist: setuptools
Requires-Dist: wheel
Requires-Dist: dotenv
Requires-Dist: pre-commit
Requires-Dist: custom-python-logger
Requires-Dist: pytest
Requires-Dist: requests
Requires-Dist: retrying
Requires-Dist: jira
Dynamic: author
Dynamic: description
Dynamic: description-content-type
Dynamic: home-page
Dynamic: license-file
Dynamic: project-url
Dynamic: requires-dist
Dynamic: requires-python
Dynamic: summary
